Changes
LICENSE
MANIFEST.in
README
setup.py
termcast_client/__init__.py
termcast_client/__main__.py
termcast_client/pity.py
termcast_client/py2compat.py
termcast_client.egg-info/PKG-INFO
termcast_client.egg-info/SOURCES.txt
termcast_client.egg-info/dependency_links.txt
termcast_client.egg-info/entry_points.txt
termcast_client.egg-info/top_level.txt