Metadata-Version: 1.1
Name: termcast-client
Version: 0.1.2
Summary: broadcast your terminal sessions for remote viewing
Home-page: https://github.com/doy/python-termcast-client
Author: Jesse Luehrs
Author-email: doy@tozt.net
License: MIT
Platform: UNKNOWN
Classifier: Development Status :: 3 - Alpha
Classifier: Environment :: Console
Classifier: License :: OSI Approved :: MIT License
Classifier: Topic :: Terminals :: Terminal Emulators/X Terminals
